gensor/__init__.py
gensor/analysis/__init__.py
gensor/analysis/outliers.py
gensor/analysis/stats.py
gensor/config.py
gensor/core/__init__.py
gensor/core/base.py
gensor/core/dataset.py
gensor/core/indexer.py
gensor/core/timeseries.py
gensor/db/__init__.py
gensor/db/connection.py
gensor/exceptions.py
gensor/io/__init__.py
gensor/io/read.py
gensor/log.py
gensor/parse/__init__.py
gensor/parse/plain.py
gensor/parse/utils.py
gensor/parse/vanessen.py
gensor/processing/__init__.py
gensor/processing/compensation.py
gensor/processing/smoothing.py
gensor/processing/transform.py
gensor/testdata/Barodiver_220427183008_BY222.csv
gensor/testdata/PB01A_moni_AV319_220427183019_AV319.csv
gensor/testdata/PB02A_plain.csv
gensor/testdata/__init__.py
py.typed
gensor-0.2.5.dist-info/LICENSE
gensor-0.2.5.dist-info/METADATA
gensor-0.2.5.dist-info/WHEEL
gensor-0.2.5.dist-info/RECORD
