Metadata-Version: 2.1
Name: gensor
Version: 0.2.5
Summary: Library for handling groundwater sensor data.
Home-page: https://github.com/zawadzkim/gensor
Author: Mateusz Zawadzki
Author-email: zawadzkimat@outlook.com
Requires-Python: >=3.11
Classifier: Programming Language :: Python :: 3
Classifier: Programming Language :: Python :: 3.11
Classifier: Programming Language :: Python :: 3.12
Requires-Dist: chardet (>=5.2.0,<6.0.0)
Requires-Dist: matplotlib (>=3.9.2,<4.0.0)
Requires-Dist: numpy (>=2.0.0,<3.0.0)
Requires-Dist: pandas (>=2.2.2,<3.0.0)
Requires-Dist: pandera (>=0.20.3,<0.21.0)
Requires-Dist: pydantic (>=2.8.2,<3.0.0)
Requires-Dist: python-dateutil (>=2.9.0.post0,<3.0.0)
Requires-Dist: scikit-learn (>=1.5.1,<2.0.0)
Requires-Dist: scipy (>=1.14.1,<2.0.0)
Requires-Dist: sqlalchemy (>=2.0.32,<3.0.0)
Project-URL: Documentation, https://zawadzkim.github.io/gensor/
Project-URL: Repository, https://github.com/zawadzkim/gensor
